gadhttpclient/__init__.py
gadhttpclient/cli.py
gadhttpclient/const/__init__.py
gadhttpclient/const/extentions.py
gadhttpclient/const/files.py
gadhttpclient/const/http.py
gadhttpclient/const/regexp.py
gadhttpclient/const/specification.py
gadhttpclient/const/symbols.py
gadhttpclient/const/syntax.py
gadhttpclient/const/templates.py
gadhttpclient/enums/__init__.py
gadhttpclient/enums/http.py
gadhttpclient/enums/python.py
gadhttpclient/enums/specification.py
gadhttpclient/enums/typing.py
gadhttpclient/mappers/__init__.py
gadhttpclient/mappers/python.py
gadhttpclient/mappers/specification.py
gadhttpclient/models/__init__.py
gadhttpclient/models/http.py
gadhttpclient/models/specification.py
gadhttpclient/os/__init__.py
gadhttpclient/os/files.py
gadhttpclient/os/folders.py
gadhttpclient/os/http.py
gadhttpclient/parsers/__init__.py
gadhttpclient/parsers/config.py
gadhttpclient/parsers/specification.py
gadhttpclient/utils/__init__.py
gadhttpclient/utils/sorting.py
gadhttpclient/utils/toml.py
tests/__init__.py
tests/test_init.py
gadhttpclient-0.0.4.dist-info/LICENSE
gadhttpclient-0.0.4.dist-info/METADATA
gadhttpclient-0.0.4.dist-info/WHEEL
gadhttpclient-0.0.4.dist-info/entry_points.txt
gadhttpclient-0.0.4.dist-info/top_level.txt
gadhttpclient-0.0.4.dist-info/RECORD
