Metadata-Version: 2.1
Name: gadhttpclient
Version: 0.0.4
Summary: A CLI tool that generates HTTP clients from an OpenAPI specification
Home-page: https://github.com/AlexDemure/gadhttpclient
Author: Alexander Grishchenko
Author-email: alexanderdemure@gmail.com
Classifier: Programming Language :: Python :: 3
Classifier: License :: OSI Approved :: MIT License
Classifier: Operating System :: OS Independent
Requires-Python: >=3.8
License-File: LICENSE
Requires-Dist: datamodel-code-generator
Requires-Dist: gadify
Requires-Dist: jinja2
Requires-Dist: pydantic
Requires-Dist: tomli
Requires-Dist: typer
